README.md
setup.py
pylnlib/Interface.py
pylnlib/Message.py
pylnlib/Script.py
pylnlib/ScriptRunner.py
pylnlib/Scrollkeeper.py
pylnlib/Sensor.py
pylnlib/Slot.py
pylnlib/Switch.py
pylnlib/Throttle.py
pylnlib/Utils.py
pylnlib/Webserver.py
pylnlib/__init__.py
pylnlib/__main__.py
pylnlib.egg-info/PKG-INFO
pylnlib.egg-info/SOURCES.txt
pylnlib.egg-info/dependency_links.txt
pylnlib.egg-info/not-zip-safe
pylnlib.egg-info/requires.txt
pylnlib.egg-info/top_level.txt
test/test_Message.py