Metadata-Version: 2.1
Name: pylnlib
Version: 0.3.0
Summary: A library to monitor LocoNet message on a serial interface
Home-page: https://varkenvarken.github.io/pylnlib/
Author: varkenvarken
Author-email: test@example.com
License: GPLv3
Platform: UNKNOWN
Classifier: Development Status :: 3 - Alpha
Classifier: Programming Language :: Python :: 3.8
Classifier: Programming Language :: Python :: 3.9
Classifier: License :: OSI Approved :: GNU General Public License v3 (GPLv3)
Classifier: Operating System :: OS Independent
Classifier: Framework :: FastAPI
Requires-Python: >=3.8
Provides-Extra: webserver
